{
  "project_info": {
    "project_number": "369561580249",
    "firebase_url": "https://first-app-e49a0-default-rtdb.firebaseio.com",
    "project_id": "first-app-e49a0",
    "storage_bucket": "first-app-e49a0.firebasestorage.app"
  },
  "client": [
    {
      "client_info": {
        "mobilesdk_app_id": "1:369561580249:android:0eccc4eafbb08fa22244c8",
        "android_client_info": {
          "package_name": "com.example.aplikasi_daftar_belanja"
        }
      },
      "oauth_client": [],
      "api_key": [
        {
          "current_key": "AIzaSyDntGCUO9PDuJguyrXK6aCQi168HjiUaYc"
        }
      ],
      "services": {
        "appinvite_service": {
          "other_platform_oauth_client": []
        }
      }
    }
  ],
  "configuration_version": "1"
}